Metadata-Version: 2.1
Name: can-j1939-ttpsc
Version: 1.0.4
Summary: Fork of SAE J1939 stack implementation, originally created by Juergen Heilgemeir
Home-page: https://github.com/ttpscmolinaf/python-can-j1939
Author: TTPSC
License: MIT
Keywords: CAN SAE J1939 J1939-FD J1939-22
Platform: any
Classifier: License :: OSI Approved :: MIT License
Classifier: Operating System :: OS Independent
Classifier: Programming Language :: Python :: 3
Classifier: Intended Audience :: Developers
Classifier: Topic :: Scientific/Engineering
License-File: LICENSE
Requires-Dist: python-can >=3.3.4
Requires-Dist: numpy >=1.17.0
Requires-Dist: pytest >=6.2.5
